python_version_check_test_dynamic_published/__init__.py
python_version_check_test_dynamic_published/cli.py
python_version_check_test_dynamic_published-0.1.1.dist-info/METADATA
python_version_check_test_dynamic_published-0.1.1.dist-info/WHEEL
python_version_check_test_dynamic_published-0.1.1.dist-info/entry_points.txt
python_version_check_test_dynamic_published-0.1.1.dist-info/RECORD
