Metadata-Version: 2.4
Name: python-version-check-test-dynamic-published
Version: 0.1.1
Summary: Add your description here
Author-email: Annie Ehler <annie.ehler.4@gmail.com>
Requires-Python: >=3.11
Requires-Dist: rich-click>=1.9.2
Requires-Dist: rich>=14.1.0
